ai_fashion_house/__init__.py
ai_fashion_house/cli.py
ai_fashion_house/create_rag.py
ai_fashion_house/agents/__init__.py
ai_fashion_house/agents/fashion_design_agent/__init__.py
ai_fashion_house/agents/fashion_design_agent/agent.py
ai_fashion_house/agents/fashion_design_agent/prompts.py
ai_fashion_house/agents/fashion_design_agent/tools.py
ai_fashion_house/agents/marketing_agent/__init__.py
ai_fashion_house/agents/marketing_agent/agent.py
ai_fashion_house/agents/marketing_agent/imagen.py
ai_fashion_house/agents/marketing_agent/prompts.py
ai_fashion_house/agents/marketing_agent/veo.py
ai_fashion_house/agents/met_rag_agent/__init__.py
ai_fashion_house/agents/met_rag_agent/agent.py
ai_fashion_house/agents/met_rag_agent/prompts.py
ai_fashion_house/agents/met_rag_agent/tools.py
ai_fashion_house/agents/search_agent/__init__.py
ai_fashion_house/agents/search_agent/agent.py
ai_fashion_house/agents/search_agent/prompts.py
ai_fashion_house/utils/__init__.py
ai_fashion_house/utils/adk_utils.py
ai_fashion_house/utils/gcp_utils.py
ai_fashion_house/utils/image_utils.py
ai_fashion_house/web/__init__.py
ai_fashion_house/web/api.py
ai_fashion_house/web/app.py
ai_fashion_house/web/web.py
ai_fashion_house/web/static/index.html
ai_fashion_house/web/static/logo.svg
ai_fashion_house-0.1.11.dist-info/METADATA
ai_fashion_house-0.1.11.dist-info/WHEEL
ai_fashion_house-0.1.11.dist-info/entry_points.txt
ai_fashion_house-0.1.11.dist-info/RECORD
