Metadata-Version: 2.4
Name: ai-fashion-house
Version: 0.1.11
Summary: AI Fashion House, A multi agent adk application for fashion design
Author-email: haruiz <henryruiz22@gmail.com>, margaretmz <margaretmz@gmail.com>
Requires-Python: >=3.11.11
Requires-Dist: aiofiles>=24.1.0
Requires-Dist: aiohttp>=3.12.13
Requires-Dist: db-dtypes>=1.4.3
Requires-Dist: deprecated>=1.2.18
Requires-Dist: google-adk>=1.3.0
Requires-Dist: google-cloud-bigquery-connection>=1.18.3
Requires-Dist: google-cloud-bigquery>=3.34.0
Requires-Dist: httpx>=0.28.1
Requires-Dist: matplotlib>=3.10.3
Requires-Dist: pandas>=2.3.0
Requires-Dist: pillow>=11.2.1
Requires-Dist: rich>=14.0.0
Requires-Dist: typer>=0.16.0
